nrtest/__init__.py
nrtest/compare.py
nrtest/execute.py
nrtest/plugin.py
nrtest/process.py
nrtest/testsuite.py
nrtest/utility.py
nrtest-0.2.5.data/scripts/nrtest
nrtest-0.2.5.dist-info/LICENSE
nrtest-0.2.5.dist-info/METADATA
nrtest-0.2.5.dist-info/WHEEL
nrtest-0.2.5.dist-info/entry_points.txt
nrtest-0.2.5.dist-info/top_level.txt
nrtest-0.2.5.dist-info/RECORD
