Metadata-Version: 2.1
Name: nrtest
Version: 0.2.5
Summary: Numerical regression testing
Home-page: https://github.com/davidchall/nrtest
Author: David Hall
Author-email: dhcrawley@gmail.com
License: MIT
Keywords: nrtest
Platform: UNKNOWN
Classifier: Development Status :: 2 - Pre-Alpha
Classifier: Intended Audience :: Developers
Classifier: License :: OSI Approved :: MIT License
Classifier: Natural Language :: English
Classifier: Programming Language :: Python :: 2
Classifier: Programming Language :: Python :: 2.7
Classifier: Programming Language :: Python :: 3
Classifier: Programming Language :: Python :: 3.4
Classifier: Programming Language :: Python :: 3.5
Classifier: Programming Language :: Python :: 3.6
Classifier: Programming Language :: Python :: 3.7
Classifier: Programming Language :: Python :: 3.8
License-File: LICENSE
Requires-Dist: six
Requires-Dist: psutil (>=2.0)
Requires-Dist: packaging
